video_service/__init__.py
video_service/cli.py
video_service/server.py
video_service/logs/video_service.log
carey_mcp_video-0.1.3.dist-info/METADATA
carey_mcp_video-0.1.3.dist-info/WHEEL
carey_mcp_video-0.1.3.dist-info/entry_points.txt
carey_mcp_video-0.1.3.dist-info/licenses/LICENSE
carey_mcp_video-0.1.3.dist-info/RECORD
