Metadata-Version: 2.4
Name: carey_mcp_video
Version: 0.1.3
Summary: An MCP server that provides video processing services
Author-email: Carey <carey@example.com>
License: MIT
License-File: LICENSE
Keywords: concatenation,frame-extraction,mcp,processing,video
Classifier: Development Status :: 4 - Beta
Classifier: Intended Audience :: Developers
Classifier: License :: OSI Approved :: MIT License
Classifier: Programming Language :: Python :: 3
Classifier: Programming Language :: Python :: 3.9
Classifier: Topic :: Multimedia :: Video
Classifier: Topic :: Software Development :: Libraries
Requires-Python: >=3.9
Requires-Dist: fastmcp>=0.4.0
Requires-Dist: loguru>=0.7.0
Requires-Dist: moviepy>=1.0.3
Requires-Dist: opencv-python>=4.8.0
Requires-Dist: requests>=2.32
Requires-Dist: tos>=2.0.0
